pypi_test_OctoSLiu/__init__.py
pypi_test_octosliu-0.1.0.dist-info/METADATA
pypi_test_octosliu-0.1.0.dist-info/WHEEL
pypi_test_octosliu-0.1.0.dist-info/RECORD
