Metadata-Version: 2.1
Name: pypi-test-octosliu
Version: 0.1.0
Summary: 
Author: Stephanie Liu
Author-email: sliu@octoml.ai
Requires-Python: >=3.8,<4.0
Classifier: Programming Language :: Python :: 3
Classifier: Programming Language :: Python :: 3.8
Classifier: Programming Language :: Python :: 3.9
Classifier: Programming Language :: Python :: 3.10
Classifier: Programming Language :: Python :: 3.11
Requires-Dist: sphinx (>=7.0.1,<8.0.0)
